molstruct/__init__.py
molstruct/__main__.py
molstruct/names.py
molstruct/outputs.py
tests/__init__.py
tests/test_outputs.py
molstruct-3.0.0.dist-info/LICENSE
molstruct-3.0.0.dist-info/METADATA
molstruct-3.0.0.dist-info/WHEEL
molstruct-3.0.0.dist-info/entry_points.txt
molstruct-3.0.0.dist-info/top_level.txt
molstruct-3.0.0.dist-info/RECORD
